[
 {
  "id": 1677204722857,
  "name": "Samsung A03",
  "description": "",
  "category": "oferts",
  "subcategory": "oferts",
  "brand": "Samsung",
  "color": "black",
  "memory": "128GB",
  "size": "155.7 mm x 74.5 mm x 7.9 mm",
  "price": "145000",
  "discount": "23",
  "images": [
   "image-1677204722770-.jpg",
   "image-1677204722830-.webp",
   "image-1677204722831-.webp",
   "image-1677204722852-.webp"
  ]
 },
 {
  "id": 1677204959245,
  "name": "Motorola G22",
  "description": "",
  "category": "oferts",
  "subcategory": "oferts",
  "brand": "Motorola",
  "color": "black",
  "memory": "128GB",
  "size": "155.7 mm x 74.5 mm x 7.9 mm",
  "price": "14500",
  "discount": "23",
  "images": [
   "image-1677205126301-.jpg",
   "image-1677205126304-.jpg",
   "image-1677205126320-.webp",
   "image-1677205126321-.jpg",
   "image-1677205126333-.webp"
  ]
 }
]